sarracenia/__init__.py
sarracenia/_version.py
sarracenia/blockmanifest.py
sarracenia/bulletin.py
sarracenia/diskqueue.py
sarracenia/featuredetection.py
sarracenia/filemetadata.py
sarracenia/instance.py
sarracenia/interruptible_sleep.py
sarracenia/make_json_serializable.py
sarracenia/pyads.py
sarracenia/rabbitmq_admin.py
sarracenia/redisqueue.py
sarracenia/sr.py
sarracenia/sr3_rotateLogsManually.py
sarracenia/sr_flow.py
sarracenia/sr_post.py
sarracenia/sr_tailf.py
sarracenia/config/__init__.py
sarracenia/config/credentials.py
sarracenia/config/publisher.py
sarracenia/config/subscription.py
sarracenia/examples/cpump/cno_trouble_f00.inc
sarracenia/examples/flow/amserver.conf
sarracenia/examples/flow/bc_trans.conf
sarracenia/examples/flow/opg.conf
sarracenia/examples/flow/poll.inc
sarracenia/examples/flow/post.inc
sarracenia/examples/flow/report.inc
sarracenia/examples/flow/sarra.inc
sarracenia/examples/flow/scheduled_aviation_wind_fax_charts.conf
sarracenia/examples/flow/sender.inc
sarracenia/examples/flow/shovel.inc
sarracenia/examples/flow/subscribe.inc
sarracenia/examples/flow/watch.inc
sarracenia/examples/flow/winnow.inc
sarracenia/examples/poll/airnow.conf
sarracenia/examples/poll/aws-nexrad.conf
sarracenia/examples/poll/copernicus_odata.conf
sarracenia/examples/poll/mail.conf
sarracenia/examples/poll/nasa-mls-nrt.conf
sarracenia/examples/poll/nasa_cmr_opendap.conf
sarracenia/examples/poll/nasa_cmr_other.conf
sarracenia/examples/poll/nasa_cmr_podaac.conf
sarracenia/examples/poll/noaa.conf
sarracenia/examples/poll/soapshc.conf
sarracenia/examples/poll/usgs.conf
sarracenia/examples/post/WMO_mesh_post.conf
sarracenia/examples/sarra/bc_trans.conf
sarracenia/examples/sarra/wmo_mesh.conf
sarracenia/examples/sender/am_send.conf
sarracenia/examples/sender/ec2collab.conf
sarracenia/examples/sender/pitcher_push.conf
sarracenia/examples/shovel/no_trouble_f00.inc
sarracenia/examples/subscribe/aws-nexrad.conf
sarracenia/examples/subscribe/dd_2mqtt.conf
metpx_sr3-3.1.0.dist-info/AUTHORS.rst
metpx_sr3-3.1.0.dist-info/LICENSE.txt
metpx_sr3-3.1.0.dist-info/METADATA
metpx_sr3-3.1.0.dist-info/WHEEL
metpx_sr3-3.1.0.dist-info/entry_points.txt
metpx_sr3-3.1.0.dist-info/top_level.txt
metpx_sr3-3.1.0.dist-info/RECORD
